kappy/kappa_std.py
kappy/kappa_common.py
kappy/__init__.py
kappy/kappa_rest.py
kappy/kappa_graph.py
kappy/dummy.cpython-310-x86_64-linux-gnu.so
kappy/bin/KappaSwitchman
kappy/bin/KaSimAgent
kappy/bin/KaSaAgent
kappy/bin/KaMoHa
kappy-4.1.2.dist-info/top_level.txt
kappy-4.1.2.dist-info/RECORD
kappy-4.1.2.dist-info/AUTHORS
kappy-4.1.2.dist-info/WHEEL
kappy-4.1.2.dist-info/METADATA
