Metadata-Version: 2.1
Name: kappy
Version: 4.1.2
Summary: Wrapper to interact with the Kappa tool suite
Home-page: https://github.com/Kappa-Dev/KappaTools.git
Author: Kappa-Dev
Author-email: kappa-dev@listes.sc.univ-paris-diderot.fr
License: LGPLv3
Platform: UNKNOWN
Classifier: License :: OSI Approved :: GNU Lesser General Public License v3 (LGPLv3)
Classifier: Topic :: Scientific/Engineering :: Bio-Informatics
Requires-Dist: requests
Requires-Dist: future
Requires-Dist: nose
